{
    "python.command.python.sortImports.title": "ഇറക്കുമതി അടുക്കുക",
    "python.command.python.startREPL.title": "REPL ആരംഭിക്കുക",
    "python.command.python.createTerminal.title": " Terminal ഉണ്ടാക്കുക",
    "python.command.python.buildWorkspaceSymbols.title": "Workspace ചിഹ്നങ്ങൾ നിർമ്മിക്കുക",
    "python.command.python.runtests.title": "എല്ലാ ടെസ്റ്റുകളും പ്രവർത്തിപ്പിക്കുക",
    "python.command.python.debugtests.title": "എല്ലാ ടെസ്റ്റുകളും ഡീബഗ് ചെയ്യുക",
    "python.command.python.execInTerminal.title": "ടെർമിനലിൽ Python ഫയൽ പ്രവർത്തിപ്പിക്കുക",
    "python.command.python.setInterpreter.title": "Interpreter തിരഞ്ഞെടുക്കുക",
    "python.command.python.switchOffInsidersChannel.title": "സ്ഥിരസ്ഥിതി ചാനലിലേക്ക് മാറുക",
    "python.command.python.switchToDailyChannel.title": "Insiders Daily ചാനലിലേക്ക് മാറുക",
    "python.command.python.switchToWeeklyChannel.title": "Insiders Weekly ചാനലിലേക്ക് മാറുക",
    "python.command.python.viewOutput.title": "Output കാണിക്കുക",
    "python.command.python.viewTestOutput.title": "Test Output കാണിക്കുക",
    "python.command.python.datascience.viewJupyterOutput.title": "Jupyter Output കാണിക്കുക",
    "python.command.python.viewLanguageServerOutput.title": "Language Server Output കാണിക്കുക",
    "python.command.python.selectAndRunTestMethod.title": "Test Method പ്രവർത്തിപ്പിക്കുക ...",
    "python.command.python.selectAndDebugTestMethod.title": "Test Method Debug ചെയ്യുക...",
    "python.command.python.selectAndRunTestFile.title": "Test File പ്രവർത്തിപ്പിക്കുക ...",
    "python.command.python.runCurrentTestFile.title": "നിലവിലുള്ള Test File പ്രവർത്തിപ്പിക്കുക",
    "python.command.python.runFailedTests.title": "പരാജയപ്പെട്ട ടെസ്റ്റുകൾ പ്രവർത്തിപ്പിക്കുക",
    "python.command.python.discoverTests.title": "ടെസ്റ്റുകൾ കണ്ടെത്തുക",
    "python.command.python.discoveringTests.title": "കണ്ടെത്തുന്നു.....",
    "python.command.python.stopTests.title": "നിർത്തുക",
    "python.command.python.configureTests.title": "ടെസ്റ്റുകൾ Configure ചെയ്യുക",
    "python.command.python.execSelectionInTerminal.title": "തിരഞ്ഞെടുത്തത് പ്രവർത്തിപ്പിക്കുക/Line in Python Terminal",
    "python.command.python.execSelectionInDjangoShell.title": "Run Selection/Line in Django Shell",
    "python.command.python.goToPythonObject.title": "Python Objectലെക്ക് പോകുക",
    "python.command.python.setLinter.title": "Linter തിരഞ്ഞെടുത്തു",
    "python.command.python.enableLinting.title": "Linting പ്രാപ്തമാക്കുക",
    "python.command.python.runLinting.title": "Linting പ്രവർത്തിപ്പിക്കുക",
    "python.command.python.datascience.debugFileInteractive.title": "Python Interactive Window ൽ നിലവിലെ ഫയൽ പ്രവർത്തിപ്പിക്കുക",
    "python.command.python.datascience.runallcells.title": "എല്ലാ സെല്ലുകളും പ്രവർത്തിപ്പിക്കുക",
    "python.command.python.datascience.notebookeditor.runallcells.title": "എല്ലാ നോട്ട്ബുക്ക് സെല്ലുകളും പ്രവർത്തിപ്പിക്കുക",
    "python.command.python.datascience.runallcellsabove.title": "മുകളിൽ പ്രവർത്തിപ്പിക്കുക",
    "python.command.python.datascience.runcellandallbelow.title": "Run Below",
    "python.command.python.datascience.runallcellsabove.palette.title": "നിലവിലെ സെല്ലിന് മുകളിൽ സെല്ലുകൾ പ്രവർത്തിപ്പിക്കുക",
    "python.command.python.datascience.runcurrentcellandallbelow.palette.title": "Run Current Cell and Below",
    "python.command.python.datascience.debugcurrentcell.palette.title": "Debug Current Cell",   
    "python.command.python.datascience.debugcell.title": "Cell Debug ചെയ്യുക",
    "python.command.python.datascience.debugstepover.title": "Step Over",
    "python.command.python.datascience.debugcontinue.title": "തുടരുക",
    "python.command.python.datascience.debugstop.title": "നിർത്തുക",
    "python.command.python.datascience.runcurrentcell.title": "നിലവിലെ സെൽ പ്രവർത്തിപ്പിക്കുക",
    "python.command.python.datascience.runcurrentcelladvance.title": "നിലവിലെ സെൽ പ്രവർത്തിപ്പിച്ചു മുന്നേറുക",
    "python.command.python.datascience.execSelectionInteractive.title": "Select ചെയ്‍തത് പ്രവർത്തിപ്പിക്കുക /Line in Python Interactive Window",
    "python.command.python.datascience.runcell.title": "Cell പ്രവർത്തിപ്പിക്കുക",
    "python.command.python.datascience.selectjupyteruri.title": "കണക്ഷനുകൾക്കായി Local അല്ലെങ്കിൽ  Remote ജൂപ്പിറ്റർ സെർവർ വ്യക്തമാക്കുക",
    "python.command.python.datascience.selectjupytercommandline.title": "Jupyter command line arguments വ്യക്തമാക്കുക",
    "python.command.python.datascience.opennotebook.title": "Notebook Editor ൽ തുറക്കുക",
    "python.command.python.datascience.importnotebookfile.title": "Python Script ലേക്ക് മാറ്റുക",
    "python.command.python.datascience.undocells.title": "Undo Last Python Interactive Action",
    "python.command.python.datascience.redocells.title": "Redo Last Python Interactive Action",
    "python.command.python.datascience.removeallcells.title": "എല്ലാ Python Interactive Cells ഉം മായ്ക്കുക",
    "python.command.python.datascience.notebookeditor.removeallcells.title": "എല്ലാ Notebook Editor Cells ഉം മായ്ക്കുക",
    "python.command.python.datascience.notebookeditor.addcellbelow.title": "Notebook File ലേക്ക് ശൂന്യമായ സെൽ ചേർക്കുക",
    "python.command.python.datascience.expandallcells.title": "എല്ലാ Python Interactive Cells വികസിപ്പിക്കുക",
    "python.command.python.datascience.addcellbelow.title": "File ലേക്ക് ശൂന്യമായ സെൽ ചേർക്കുക",
    "python.snippet.launch.standard.label": "Python: നിലവിലെ File",
    "python.snippet.launch.attachpid.label": "Python: Process Id ഉപയോഗിച്ച് അറ്റാച്ചുചെയ്യുക",
    "python.snippet.launch.pyramid.label": "Python: Pyramid Application",
    "LanguageService.bannerMessage": "Python Language Server നിങ്ങൾക്കായി എങ്ങനെ പ്രവർത്തിക്കുന്നുവെന്ന് ഞങ്ങളോട് പറയാൻ 2 മിനിറ്റ് എടുക്കാമോ?",
    "LanguageService.bannerLabelYes": "അതെ, ഇപ്പോൾ സർവേ നടത്തുക",
    "LanguageService.bannerLabelNo": "വേണ്ട, നന്ദി",
    "LanguageService.lsFailedToStart": "ഭാഷാ സെർവർ ആരംഭിക്കുന്നതിൽ ഞങ്ങൾക്ക് ഒരു പ്രശ്‌നം നേരിട്ടു. ബദലിലേക്ക് മടങ്ങുന്നു, ജെഡി. വിശദാംശങ്ങൾക്ക് Python Output Panel പരിശോധിക്കുക.",
    "LanguageService.lsFailedToDownload": "ഭാഷാ സെർവർ ഡൗൺലോഡുചെയ്യുന്നതിൽ ഞങ്ങൾക്ക് ഒരു പ്രശ്‌നം നേരിട്ടു. ബദലിലേക്ക് മടങ്ങുന്നു, ജെഡി. വിശദാംശങ്ങൾക്ക് Python Output പാനൽ പരിശോധിക്കുക.",
    "LanguageService.lsFailedToExtract": "ഭാഷാ സെർവർ എക്‌സ്‌ട്രാക്റ്റുചെയ്യുന്നതിൽ ഞങ്ങൾക്ക് ഒരു പ്രശ്‌നം നേരിട്ടു. ബദലിലേക്ക് മടങ്ങുന്നു, ജെഡി. വിശദാംശങ്ങൾക്ക് Python Output പാനൽ പരിശോധിക്കുക.",
    "DataScience.unknownMimeTypeFormat": "Mime type {0} നിലവിൽ പിന്തുണയ്‌ക്കുന്നില്ല.",
    "DataScience.sessionDisposed": "Code എക്സിക്യൂട്ട് ചെയ്യാൻ കഴിയില്ല, സെഷൻ തീർത്തു.",
    "DataScience.passwordFailure": "Password Protection Serverലേക്ക് കണക്റ്റുചെയ്യുന്നതിൽ പരാജയപ്പെട്ടു. Password ശരിയാണോയെന്ന് പരിശോധിക്കുക.",
    "DataScience.exportDialogTitle": "Jupyter Notebook ലേക്ക് കയറ്റുമതി ചെയ്യുക",
    "DataScience.exportDialogFailed": "notebook കയറ്റുമതി ചെയ്യുന്നതിൽ പരാജയപ്പെട്ടു . {0}",
    "DataScience.exportOpenQuestion": "Browser ൽ തുറക്കുക",
    "DataScience.exportOpenQuestion1": "Editor ൽ തുറക്കുക",
    "DataScience.collapseInputTooltip": "input block ചുരുക്കുക",
    "DataScience.collapseVariableExplorerTooltip": "Jupyter കേർണലിൽ സജീവമായ വേരിയബിളുകൾ മറയ്‌ക്കുക",
    "DataScience.close": "അടയ്ക്കുക",
    "DataScience.reloadRequired": "പുതിയ ക്രമീകരണങ്ങൾ പ്രാബല്യത്തിൽ വരുന്നതിന് ദയവായി window വീണ്ടും ലോഡുചെയ്യുക.",
    "DataScience.notebookCheckForImportNo": "പിന്നീട്",
    "DataScience.notebookCheckForImportDontAskAgain": "വീണ്ടും ചോദിക്കരുത്",
    "DataScience.notebookCheckForImportTitle": "Python കോഡിലേക്ക് Jupyter Notebook ഇറക്കുമതി ചെയ്യാൻ നിങ്ങൾ ആഗ്രഹിക്കുന്നുണ്ടോ?",
    "DataScience.jupyterNotSupported": "Jupyter ആരംഭിക്കാൻ കഴിയില്ല. Jupyter കണ്ടെത്താൻ ശ്രമിക്കുന്നതിൽ പിശക്: {0}",
    "DataScience.jupyterNbConvertNotSupported": "Notebookകൾ ഇറക്കുമതി ചെയ്യുന്നതിന് Jupyter nbconvert ഇൻസ്റ്റാൾ ചെയ്യേണ്ടതുണ്ട്.",
    "DataScience.jupyterLaunchNoURL": "സമാരംഭിച്ച Jupyter Notebook സെർവറിന്റെ URL കണ്ടെത്തുന്നതിൽ പരാജയപ്പെട്ടു",
    "DataScience.jupyterLaunchTimedOut": "കൃത്യസമയത്ത് സമാരംഭിക്കുന്നതിൽ Jupyter Notebook സെർവർ പരാജയപ്പെട്ടു",
    "DataScience.jupyterSelfCertEnable": "അതെ, എന്തായാലും ബന്ധിപ്പിക്കുക",
    "DataScience.jupyterSelfCertClose": "ഇല്ല, കണക്ഷൻ അടയ്‌ക്കുക",
    "DataScience.jupyterServerCrashed": "Jupyter server തകർന്നു. ബന്ധിപ്പിക്കാൻ കഴിയില്ല. \r\nError code from jupyter: {0}",
    "DataScience.pythonInteractiveHelpLink": "കൂടുതൽ സഹായം നേടുക",
    "DataScience.startingJupyter": "Jupyter server ആരംഭക്കുന്നു",
    "DataScience.connectingToJupyter": "Jupyter server ലേക്ക് connect ചെയ്യുന്നു ",
    "Interpreters.RefreshingInterpreters": "Python Interpreters പുതുക്കുന്നു",
    "Interpreters.condaInheritEnvMessage": "നിങ്ങൾ ഒരു Conda environment ഉപയോഗിക്കുന്നതായി ഞങ്ങൾ ശ്രദ്ധിച്ചു. Integreted Terminal ൽ ഈ പരിതസ്ഥിതിയിൽ നിങ്ങൾക്ക് പ്രശ്നങ്ങൾ നേരിടുന്നുണ്ടെങ്കിൽ, നിങ്ങളുടെ ഉപയോക്തൃ ക്രമീകരണങ്ങളിൽ Python വിപുലീകരണം change \"terminal.integrated.inheritEnv change\" തെറ്റായി മാറ്റാൻ അനുവദിക്കാൻ ഞങ്ങൾ ശുപാർശ ചെയ്യുന്നു.",
    "Common.doNotShowAgain": "വീണ്ടും കാണിക്കരുത്",
    "Common.reload": "വീണ്ടും ലോഡുചെയ്യുക",
    "Common.moreInfo": "കൂടുതൽ വിവരങ്ങൾ",
    "ExtensionSurveyBanner.bannerMessage": "Python Extensions നിങ്ങൾക്കായി എങ്ങനെ പ്രവർത്തിക്കുന്നുവെന്ന് ഞങ്ങളോട് പറയാൻ 2 മിനിറ്റ് എടുക്കാമോ?",
    "ExtensionSurveyBanner.maybeLater": "ഒരു പക്ഷെ പിന്നീട്",
    "ExtensionChannels.installationCompleteMessage": "പൂർത്തിയായി.",
    "ExtensionChannels.yesWeekly": "അതെ, പ്രതിവാര",
    "ExtensionChannels.yesDaily": "അതെ, ദിവസവും",
    "ExtensionChannels.promptMessage": "നിങ്ങൾ Visual Studio Code Insiders ഉപയോഗിക്കുന്നത് ഞങ്ങൾ ശ്രദ്ധിച്ചു. Python വിപുലീകരണത്തിന്റെ Insiders നിർമ്മിക്കാൻ‌ നിങ്ങൾ‌ താൽ‌പ്പര്യപ്പെടുന്നോ?",
    "ExtensionChannels.reloadToUseInsidersMessage": "Python Extesion ന്റെ Insiders ബിൽഡ് ഉപയോഗിക്കുന്നതിന് Visual  Studio Code വീണ്ടും ലോഡുചെയ്യുക.",
    "ExtensionChannels.downloadCompletedOutputMessage": "Insiders build download പൂർത്തിയാക്കി.",
    "ExtensionChannels.startingDownloadOutputMessage": "Insiders build നു വേണ്ടിയുള്ള download തുടങ്ങുന്നു .",
    "Interpreters.environmentPromptMessage": "ഒരു പുതിയ വെർച്വൽ പരിസ്ഥിതി സൃഷ്ടിച്ചതായി ഞങ്ങൾ ശ്രദ്ധിച്ചു. വർക്ക്‌സ്‌പെയ്‌സ് ഫോൾഡറിനായി ഇത് തിരഞ്ഞെടുക്കാൻ നിങ്ങൾ ആഗ്രഹിക്കുന്നുണ്ടോ?",
    "DataScience.reloadAfterChangingJupyterServerConnection": "Jupyter Server കണക്ഷൻ മാറ്റുമ്പോൾ ദയവായി VS Code വീണ്ടും ലോഡുചെയ്യുക.",
    "DataScience.restartKernelMessage": "IPython Kernal പുനരാരംഭിക്കാൻ നിങ്ങൾ ആഗ്രഹിക്കുന്നുണ്ടോ? എല്ലാ Variableകളും നഷ്ടപ്പെടും.",
    "DataScience.jupyterSelectURIRemoteDetail": "നിലവിലുള്ള സെർവറിന്റെ URI വ്യക്തമാക്കുക"
}
